MANIFEST.in
README.rst
setup.py
felis_python1/__init__.py
felis_python1/util.py
felis_python1.egg-info/PKG-INFO
felis_python1.egg-info/SOURCES.txt
felis_python1.egg-info/dependency_links.txt
felis_python1.egg-info/not-zip-safe
felis_python1.egg-info/requires.txt
felis_python1.egg-info/top_level.txt
felis_python1/lectures/01_Variable attribution_and_Math.ipynb
felis_python1/lectures/02_Built-in functions and Slicing.ipynb
felis_python1/lectures/03_Libraries and Conditions.ipynb
felis_python1/lectures/04_Loops and List Comprehention.ipynb
felis_python1/lectures/05_Functions.ipynb
felis_python1/lectures/06_Classes.ipynb
felis_python1/lectures/06_Exceptions.ipynb
felis_python1/lectures/07_PEP8.ipynb