Metadata-Version: 1.0
Name: felis-python1
Version: 0.0.5
Summary: Lecture notes for Python 1 at University of Freiburg.
Home-page: UNKNOWN
Author: Mirko Mälicke
Author-email: mirko.maelicke@felis.uni-freiburg.de
License: MIT
Platform: UNKNOWN
